streamlit_imagegrid/__init__.py
streamlit_imagegrid/example.py
streamlit_imagegrid/frontend/dist/index.html
streamlit_imagegrid/frontend/dist/assets/index-BDTTHegY.js
streamlit_imagegrid/frontend/dist/assets/index-BLVYpR1b.js
streamlit_imagegrid/frontend/dist/assets/index-BVVD09Cw.js
streamlit_imagegrid/frontend/dist/assets/index-CpW4nSwf.js
streamlit_imagegrid/frontend/dist/assets/index-DBEr_dO3.js
streamlit_imagegrid/frontend/dist/assets/index-DhBCCDOT.js
streamlit_imagegrid/frontend/dist/assets/index-HLyEJVR5.js
streamlit_imagegrid/frontend/dist/assets/index-LYDz7A-0.js
streamlit_imagegrid/frontend/dist/assets/index-Xa4o5SJg.css
streamlit_imagegrid/frontend/dist/assets/index-cAkN8yIY.js
streamlit_imagegrid/frontend/dist/assets/index-cdVf0a8X.js
streamlit_imagegrid-0.0.7.dist-info/LICENSE
streamlit_imagegrid-0.0.7.dist-info/METADATA
streamlit_imagegrid-0.0.7.dist-info/WHEEL
streamlit_imagegrid-0.0.7.dist-info/top_level.txt
streamlit_imagegrid-0.0.7.dist-info/RECORD
