Metadata-Version: 2.1
Name: streamlit_imagegrid
Version: 0.0.7
Summary: Streamlit component that allows you to do image/video grid
Home-page: 
Author: Midhun Harikumar
Author-email: midhunharikumar@outlook.com.com
Requires-Python: >=3.9
License-File: LICENSE
Requires-Dist: streamlit>=0.63
